colorviews/__init__.py
colorviews/colors.py
colorviews/names.py
colorviews/utils.py
colorviews/views.py
colorviews-0.1a1.dist-info/LICENSE.md
colorviews-0.1a1.dist-info/METADATA
colorviews-0.1a1.dist-info/WHEEL
colorviews-0.1a1.dist-info/top_level.txt
colorviews-0.1a1.dist-info/RECORD
