Metadata-Version: 2.1
Name: colorviews
Version: 0.1a1
Summary: A simple module to handle colors
Home-page: https://github.com/ju-sh/colorviews
Author: Julin S
Author-email: 
License: UNKNOWN
Project-URL: Changelog, https://github.com/ju-sh/colorviews/blob/master/CHANGELOG.md
Project-URL: Issue Tracker, https://github.com/ju-sh/colorviews/issues
Platform: UNKNOWN
Classifier: Programming Language :: Python :: 3
Classifier: Programming Language :: Python :: 3.6
Classifier: Programming Language :: Python :: 3.7
Classifier: Programming Language :: Python :: 3.8
Classifier: Programming Language :: Python :: 3.9
Requires-Python: >=3.6
